segregation/__init__.py
segregation/_base.py
segregation/batch/__init__.py
segregation/batch/batch_compute.py
segregation/decomposition/__init__.py
segregation/decomposition/decompose_segregation.py
segregation/dynamics/__init__.py
segregation/dynamics/divergence_profile.py
segregation/dynamics/segregation_profile.py
segregation/inference/__init__.py
segregation/inference/comparative.py
segregation/inference/inference_wrappers.py
segregation/inference/randomization.py
segregation/local/__init__.py
segregation/local/local_distortion.py
segregation/local/local_multi_diversity.py
segregation/local/local_multi_entropy.py
segregation/local/local_multi_location_quotient.py
segregation/local/local_multi_simpson_concentration.py
segregation/local/local_multi_simpsons_interaction.py
segregation/local/local_relative_centralization.py
segregation/multigroup/__init__.py
segregation/multigroup/multi_dissim.py
segregation/multigroup/multi_divergence.py
segregation/multigroup/multi_diversity.py
segregation/multigroup/multi_gini.py
segregation/multigroup/multi_global_distortion.py
segregation/multigroup/multi_info_theory.py
segregation/multigroup/multi_norm_exposure.py
segregation/multigroup/multi_relative_diversity.py
segregation/multigroup/multi_squared_coef_var.py
segregation/multigroup/simpsons_concentration.py
segregation/multigroup/simpsons_interaction.py
segregation/network/__init__.py
segregation/network/network.py
segregation/singlegroup/__init__.py
segregation/singlegroup/absolute_centralization.py
segregation/singlegroup/absolute_clustering.py
segregation/singlegroup/absolute_concentration.py
segregation/singlegroup/atkinson.py
segregation/singlegroup/bias_corrected_dissim.py
segregation/singlegroup/boundary_spatial_dissim.py
segregation/singlegroup/conprof.py
segregation/singlegroup/correlationr.py
segregation/singlegroup/delta.py
segregation/singlegroup/density_corrected_dissim.py
segregation/singlegroup/dissim.py
segregation/singlegroup/dx_interaction.py
segregation-2.5.1.dist-info/LICENSE.txt
segregation-2.5.1.dist-info/METADATA
segregation-2.5.1.dist-info/WHEEL
segregation-2.5.1.dist-info/top_level.txt
segregation-2.5.1.dist-info/RECORD
